[{"course_code": "ENGL732", "course_name": "Course Name ENGL732"}, {"course_code": "MGMT776", "course_name": "Course Name MGMT776"}, {"course_code": "LANG234", "course_name": "Course Name LANG234"}, {"course_code": "MATH702", "course_name": "Course Name MATH702"}, {"course_code": "MGMT335", "course_name": "Course Name MGMT335"}, {"course_code": "PSYC149", "course_name": "Course Name PSYC149"}, {"course_code": "BIOL401", "course_name": "Course Name BIOL401"}, {"course_code": "ECON825", "course_name": "Course Name ECON825"}, {"course_code": "ECON153", "course_name": "Course Name ECON153"}, {"course_code": "ECON250", "course_name": "Course Name ECON250"}, {"course_code": "HIST814", "course_name": "Course Name HIST814"}, {"course_code": "PSYC549", "course_name": "Course Name PSYC549"}, {"course_code": "COMP950", "course_name": "Course Name COMP950"}, {"course_code": "ENGL308", "course_name": "Course Name ENGL308"}, {"course_code": "MATH982", "course_name": "Course Name MATH982"}, {"course_code": "PSYC761", "course_name": "Course Name PSYC761"}, {"course_code": "BIOL775", "course_name": "Course Name BIOL775"}, {"course_code": "ECON561", "course_name": "Course Name ECON561"}, {"course_code": "LANG984", "course_name": "Course Name LANG984"}, {"course_code": "MATH706", "course_name": "Course Name MATH706"}, {"course_code": "LANG801", "course_name": "Course Name LANG801"}, {"course_code": "PHYS217", "course_name": "Course Name PHYS217"}, {"course_code": "MGMT607", "course_name": "Course Name MGMT607"}, {"course_code": "BIOL814", "course_name": "Course Name BIOL814"}, {"course_code": "PSYC338", "course_name": "Course Name PSYC338"}, {"course_code": "BIOL845", "course_name": "Course Name BIOL845"}, {"course_code": "MATH957", "course_name": "Course Name MATH957"}, {"course_code": "MATH539", "course_name": "Course Name MATH539"}, {"course_code": "ENGL743", "course_name": "Course Name ENGL743"}, {"course_code": "HIST593", "course_name": "Course Name HIST593"}, {"course_code": "SWEN797", "course_name": "Course Name SWEN797"}, {"course_code": "LANG298", "course_name": "Course Name LANG298"}, {"course_code": "ECON477", "course_name": "Course Name ECON477"}, {"course_code": "ENGL125", "course_name": "Course Name ENGL125"}, {"course_code": "BIOL411", "course_name": "Course Name BIOL411"}, {"course_code": "ECON277", "course_name": "Course Name ECON277"}, {"course_code": "COMP189", "course_name": "Course Name COMP189"}, {"course_code": "SWEN212", "course_name": "Course Name SWEN212"}, {"course_code": "ECON217", "course_name": "Course Name ECON217"}, {"course_code": "MATH975", "course_name": "Course Name MATH975"}, {"course_code": "PSYC654", "course_name": "Course Name PSYC654"}, {"course_code": "ENGL711", "course_name": "Course Name ENGL711"}, {"course_code": "PHYS566", "course_name": "Course Name PHYS566"}, {"course_code": "COMP943", "course_name": "Course Name COMP943"}, {"course_code": "HIST488", "course_name": "Course Name HIST488"}, {"course_code": "PSYC301", "course_name": "Course Name PSYC301"}, {"course_code": "SWEN495", "course_name": "Course Name SWEN495"}, {"course_code": "HIST391", "course_name": "Course Name HIST391"}, {"course_code": "BIOL257", "course_name": "Course Name BIOL257"}, {"course_code": "BIOL179", "course_name": "Course Name BIOL179"}, {"course_code": "MGMT829", "course_name": "Course Name MGMT829"}, {"course_code": "PSYC998", "course_name": "Course Name PSYC998"}, {"course_code": "MGMT595", "course_name": "Course Name MGMT595"}, {"course_code": "HIST874", "course_name": "Course Name HIST874"}, {"course_code": "COMP281", "course_name": "Course Name COMP281"}, {"course_code": "ECON820", "course_name": "Course Name ECON820"}, {"course_code": "BIOL528", "course_name": "Course Name BIOL528"}, {"course_code": "HIST706", "course_name": "Course Name HIST706"}, {"course_code": "COMP810", "course_name": "Course Name COMP810"}, {"course_code": "PHYS476", "course_name": "Course Name PHYS476"}, {"course_code": "BIOL370", "course_name": "Course Name BIOL370"}, {"course_code": "HIST721", "course_name": "Course Name HIST721"}, {"course_code": "PHYS405", "course_name": "Course Name PHYS405"}, {"course_code": "PHYS416", "course_name": "Course Name PHYS416"}, {"course_code": "ECON189", "course_name": "Course Name ECON189"}, {"course_code": "LANG473", "course_name": "Course Name LANG473"}, {"course_code": "BIOL813", "course_name": "Course Name BIOL813"}, {"course_code": "ENGL881", "course_name": "Course Name ENGL881"}, {"course_code": "MGMT345", "course_name": "Course Name MGMT345"}, {"course_code": "COMP717", "course_name": "Course Name COMP717"}, {"course_code": "ECON495", "course_name": "Course Name ECON495"}, {"course_code": "PHYS793", "course_name": "Course Name PHYS793"}, {"course_code": "COMP386", "course_name": "Course Name COMP386"}, {"course_code": "MATH219", "course_name": "Course Name MATH219"}, {"course_code": "MATH484", "course_name": "Course Name MATH484"}, {"course_code": "ENGL829", "course_name": "Course Name ENGL829"}, {"course_code": "ENGL387", "course_name": "Course Name ENGL387"}, {"course_code": "MATH451", "course_name": "Course Name MATH451"}, {"course_code": "ENGL697", "course_name": "Course Name ENGL697"}, {"course_code": "MGMT833", "course_name": "Course Name MGMT833"}, {"course_code": "LANG709", "course_name": "Course Name LANG709"}, {"course_code": "BIOL520", "course_name": "Course Name BIOL520"}, {"course_code": "ENGL581", "course_name": "Course Name ENGL581"}, {"course_code": "COMP804", "course_name": "Course Name COMP804"}, {"course_code": "MATH974", "course_name": "Course Name MATH974"}, {"course_code": "ENGL680", "course_name": "Course Name ENGL680"}, {"course_code": "SWEN100", "course_name": "Course Name SWEN100"}, {"course_code": "ECON737", "course_name": "Course Name ECON737"}, {"course_code": "LANG307", "course_name": "Course Name LANG307"}, {"course_code": "HIST481", "course_name": "Course Name HIST481"}, {"course_code": "COMP692", "course_name": "Course Name COMP692"}, {"course_code": "MATH209", "course_name": "Course Name MATH209"}, {"course_code": "LANG339", "course_name": "Course Name LANG339"}, {"course_code": "ENGL613", "course_name": "Course Name ENGL613"}, {"course_code": "HIST827", "course_name": "Course Name HIST827"}, {"course_code": "SWEN560", "course_name": "Course Name SWEN560"}, {"course_code": "ENGL122", "course_name": "Course Name ENGL122"}, {"course_code": "MGMT706", "course_name": "Course Name MGMT706"}, {"course_code": "ENGL857", "course_name": "Course Name ENGL857"}, {"course_code": "ENGL230", "course_name": "Course Name ENGL230"}, {"course_code": "BIOL898", "course_name": "Course Name BIOL898"}, {"course_code": "PSYC724", "course_name": "Course Name PSYC724"}, {"course_code": "LANG798", "course_name": "Course Name LANG798"}, {"course_code": "MATH354", "course_name": "Course Name MATH354"}, {"course_code": "ENGL275", "course_name": "Course Name ENGL275"}, {"course_code": "MGMT535", "course_name": "Course Name MGMT535"}, {"course_code": "ENGL337", "course_name": "Course Name ENGL337"}, {"course_code": "HIST687", "course_name": "Course Name HIST687"}, {"course_code": "PHYS350", "course_name": "Course Name PHYS350"}, {"course_code": "ENGL867", "course_name": "Course Name ENGL867"}, {"course_code": "HIST842", "course_name": "Course Name HIST842"}, {"course_code": "BIOL473", "course_name": "Course Name BIOL473"}, {"course_code": "BIOL566", "course_name": "Course Name BIOL566"}, {"course_code": "BIOL335", "course_name": "Course Name BIOL335"}, {"course_code": "SWEN930", "course_name": "Course Name SWEN930"}, {"course_code": "PHYS611", "course_name": "Course Name PHYS611"}, {"course_code": "MATH890", "course_name": "Course Name MATH890"}, {"course_code": "PSYC526", "course_name": "Course Name PSYC526"}, {"course_code": "BIOL590", "course_name": "Course Name BIOL590"}, {"course_code": "PHYS952", "course_name": "Course Name PHYS952"}, {"course_code": "LANG429", "course_name": "Course Name LANG429"}, {"course_code": "ENGL306", "course_name": "Course Name ENGL306"}, {"course_code": "PSYC438", "course_name": "Course Name PSYC438"}, {"course_code": "SWEN272", "course_name": "Course Name SWEN272"}, {"course_code": "COMP811", "course_name": "Course Name COMP811"}, {"course_code": "COMP170", "course_name": "Course Name COMP170"}, {"course_code": "COMP511", "course_name": "Course Name COMP511"}, {"course_code": "BIOL325", "course_name": "Course Name BIOL325"}, {"course_code": "MATH717", "course_name": "Course Name MATH717"}, {"course_code": "BIOL276", "course_name": "Course Name BIOL276"}, {"course_code": "SWEN620", "course_name": "Course Name SWEN620"}, {"course_code": "BIOL232", "course_name": "Course Name BIOL232"}, {"course_code": "ENGL324", "course_name": "Course Name ENGL324"}, {"course_code": "ECON435", "course_name": "Course Name ECON435"}, {"course_code": "MATH334", "course_name": "Course Name MATH334"}, {"course_code": "HIST559", "course_name": "Course Name HIST559"}, {"course_code": "ECON370", "course_name": "Course Name ECON370"}, {"course_code": "MGMT395", "course_name": "Course Name MGMT395"}, {"course_code": "SWEN541", "course_name": "Course Name SWEN541"}, {"course_code": "BIOL470", "course_name": "Course Name BIOL470"}, {"course_code": "MATH691", "course_name": "Course Name MATH691"}, {"course_code": "MATH477", "course_name": "Course Name MATH477"}, {"course_code": "PSYC196", "course_name": "Course Name PSYC196"}, {"course_code": "HIST448", "course_name": "Course Name HIST448"}, {"course_code": "MGMT547", "course_name": "Course Name MGMT547"}, {"course_code": "ENGL278", "course_name": "Course Name ENGL278"}, {"course_code": "ENGL982", "course_name": "Course Name ENGL982"}, {"course_code": "SWEN872", "course_name": "Course Name SWEN872"}, {"course_code": "MATH560", "course_name": "Course Name MATH560"}, {"course_code": "LANG957", "course_name": "Course Name LANG957"}, {"course_code": "MATH479", "course_name": "Course Name MATH479"}, {"course_code": "HIST529", "course_name": "Course Name HIST529"}, {"course_code": "HIST683", "course_name": "Course Name HIST683"}, {"course_code": "HIST729", "course_name": "Course Name HIST729"}, {"course_code": "LANG772", "course_name": "Course Name LANG772"}, {"course_code": "PSYC964", "course_name": "Course Name PSYC964"}, {"course_code": "HIST207", "course_name": "Course Name HIST207"}, {"course_code": "COMP269", "course_name": "Course Name COMP269"}, {"course_code": "ECON781", "course_name": "Course Name ECON781"}, {"course_code": "MATH987", "course_name": "Course Name MATH987"}, {"course_code": "PHYS875", "course_name": "Course Name PHYS875"}, {"course_code": "MATH755", "course_name": "Course Name MATH755"}, {"course_code": "ENGL493", "course_name": "Course Name ENGL493"}, {"course_code": "SWEN304", "course_name": "Course Name SWEN304"}, {"course_code": "ECON416", "course_name": "Course Name ECON416"}, {"course_code": "ENGL580", "course_name": "Course Name ENGL580"}, {"course_code": "HIST862", "course_name": "Course Name HIST862"}, {"course_code": "SWEN863", "course_name": "Course Name SWEN863"}, {"course_code": "BIOL502", "course_name": "Course Name BIOL502"}, {"course_code": "COMP665", "course_name": "Course Name COMP665"}, {"course_code": "BIOL940", "course_name": "Course Name BIOL940"}, {"course_code": "LANG611", "course_name": "Course Name LANG611"}, {"course_code": "PHYS597", "course_name": "Course Name PHYS597"}, {"course_code": "MATH826", "course_name": "Course Name MATH826"}, {"course_code": "BIOL258", "course_name": "Course Name BIOL258"}, {"course_code": "ENGL798", "course_name": "Course Name ENGL798"}, {"course_code": "ECON172", "course_name": "Course Name ECON172"}, {"course_code": "COMP225", "course_name": "Course Name COMP225"}, {"course_code": "MATH983", "course_name": "Course Name MATH983"}, {"course_code": "MGMT681", "course_name": "Course Name MGMT681"}, {"course_code": "LANG475", "course_name": "Course Name LANG475"}, {"course_code": "COMP507", "course_name": "Course Name COMP507"}, {"course_code": "SWEN796", "course_name": "Course Name SWEN796"}, {"course_code": "BIOL129", "course_name": "Course Name BIOL129"}, {"course_code": "MGMT570", "course_name": "Course Name MGMT570"}, {"course_code": "MATH947", "course_name": "Course Name MATH947"}, {"course_code": "MGMT906", "course_name": "Course Name MGMT906"}, {"course_code": "COMP402", "course_name": "Course Name COMP402"}, {"course_code": "SWEN883", "course_name": "Course Name SWEN883"}, {"course_code": "LANG452", "course_name": "Course Name LANG452"}, {"course_code": "SWEN137", "course_name": "Course Name SWEN137"}, {"course_code": "LANG192", "course_name": "Course Name LANG192"}, {"course_code": "SWEN374", "course_name": "Course Name SWEN374"}, {"course_code": "PSYC512", "course_name": "Course Name PSYC512"}, {"course_code": "PSYC833", "course_name": "Course Name PSYC833"}, {"course_code": "BIOL222", "course_name": "Course Name BIOL222"}, {"course_code": "MGMT283", "course_name": "Course Name MGMT283"}, {"course_code": "MATH173", "course_name": "Course Name MATH173"}, {"course_code": "HIST660", "course_name": "Course Name HIST660"}, {"course_code": "HIST561", "course_name": "Course Name HIST561"}]