[{"user_id": 10034676, "course_code": "LANG772"}, {"user_id": 10034676, "course_code": "ECON561"}, {"user_id": 10034676, "course_code": "MGMT776"}, {"user_id": 10034676, "course_code": "HIST862"}, {"user_id": 10034671, "course_code": "ECON435"}, {"user_id": 10034671, "course_code": "BIOL814"}, {"user_id": 10034671, "course_code": "MATH755"}, {"user_id": 10034671, "course_code": "BIOL470"}, {"user_id": 10034678, "course_code": "ENGL581"}, {"user_id": 10034678, "course_code": "ENGL275"}, {"user_id": 10034678, "course_code": "BIOL129"}, {"user_id": 10034678, "course_code": "BIOL502"}, {"user_id": 10034704, "course_code": "MGMT607"}, {"user_id": 10034704, "course_code": "PHYS350"}, {"user_id": 10034704, "course_code": "COMP943"}, {"user_id": 10034704, "course_code": "LANG709"}, {"user_id": 10034693, "course_code": "COMP717"}, {"user_id": 10034693, "course_code": "ECON477"}, {"user_id": 10034693, "course_code": "SWEN100"}, {"user_id": 10034693, "course_code": "LANG798"}, {"user_id": 10034690, "course_code": "PHYS611"}, {"user_id": 10034690, "course_code": "COMP281"}, {"user_id": 10034690, "course_code": "MGMT829"}, {"user_id": 10034690, "course_code": "ENGL308"}, {"user_id": 10034681, "course_code": "LANG429"}, {"user_id": 10034681, "course_code": "PSYC512"}, {"user_id": 10034681, "course_code": "ENGL697"}, {"user_id": 10034681, "course_code": "BIOL222"}, {"user_id": 10034677, "course_code": "ENGL387"}, {"user_id": 10034677, "course_code": "PHYS875"}, {"user_id": 10034673, "course_code": "LANG298"}, {"user_id": 10034673, "course_code": "PSYC196"}, {"user_id": 10034707, "course_code": "BIOL528"}, {"user_id": 10034707, "course_code": "COMP692"}, {"user_id": 10034707, "course_code": "COMP269"}, {"user_id": 10034675, "course_code": "ENGL857"}, {"user_id": 10034675, "course_code": "PSYC526"}, {"user_id": 10034684, "course_code": "ECON250"}, {"user_id": 10034684, "course_code": "ENGL743"}, {"user_id": 10034684, "course_code": "COMP189"}, {"user_id": 10034694, "course_code": "LANG234"}, {"user_id": 10034692, "course_code": "ENGL982"}, {"user_id": 10034692, "course_code": "MATH987"}, {"user_id": 10034699, "course_code": "ECON825"}, {"user_id": 10034699, "course_code": "PSYC998"}, {"user_id": 10034699, "course_code": "MATH334"}, {"user_id": 10034687, "course_code": "PHYS952"}, {"user_id": 10034687, "course_code": "PSYC964"}, {"user_id": 10034687, "course_code": "SWEN872"}, {"user_id": 10034702, "course_code": "MATH947"}, {"user_id": 10034705, "course_code": "ENGL613"}, {"user_id": 10034705, "course_code": "ENGL324"}, {"user_id": 10034705, "course_code": "PSYC724"}, {"user_id": 10034686, "course_code": "COMP402"}, {"user_id": 10034686, "course_code": "BIOL590"}, {"user_id": 10034686, "course_code": "HIST874"}, {"user_id": 10034679, "course_code": "MGMT706"}, {"user_id": 10034701, "course_code": "BIOL232"}, {"user_id": 10034682, "course_code": "SWEN863"}, {"user_id": 10034688, "course_code": "PSYC438"}, {"user_id": 10034688, "course_code": "ENGL680"}, {"user_id": 10034670, "course_code": "HIST448"}, {"user_id": 10034670, "course_code": "BIOL566"}, {"user_id": 10034670, "course_code": "COMP511"}, {"user_id": 10034670, "course_code": "MATH702"}, {"user_id": 10034680, "course_code": "HIST529"}, {"user_id": 10034680, "course_code": "COMP507"}, {"user_id": 10034696, "course_code": "MGMT595"}, {"user_id": 10034696, "course_code": "PHYS566"}, {"user_id": 10034691, "course_code": "PHYS476"}, {"user_id": 10034691, "course_code": "LANG984"}, {"user_id": 10034691, "course_code": "HIST706"}, {"user_id": 10034691, "course_code": "MGMT395"}, {"user_id": 10034685, "course_code": "BIOL276"}, {"user_id": 10034685, "course_code": "SWEN797"}, {"user_id": 10034685, "course_code": "BIOL520"}, {"user_id": 10034685, "course_code": "LANG307"}, {"user_id": 10034695, "course_code": "SWEN620"}, {"user_id": 10034695, "course_code": "ENGL337"}, {"user_id": 10034698, "course_code": "HIST842"}, {"user_id": 10034698, "course_code": "ECON370"}, {"user_id": 10034698, "course_code": "ENGL798"}, {"user_id": 10034683, "course_code": "ECON153"}, {"user_id": 10034683, "course_code": "BIOL335"}, {"user_id": 10034683, "course_code": "BIOL898"}, {"user_id": 10034683, "course_code": "SWEN272"}, {"user_id": 10034709, "course_code": "MATH209"}, {"user_id": 10034709, "course_code": "COMP170"}, {"user_id": 10034703, "course_code": "HIST660"}, {"user_id": 10034703, "course_code": "ENGL493"}, {"user_id": 10034703, "course_code": "ENGL278"}, {"user_id": 10034703, "course_code": "MATH957"}, {"user_id": 10034700, "course_code": "ECON416"}, {"user_id": 10034700, "course_code": "MATH974"}, {"user_id": 10034697, "course_code": "HIST827"}, {"user_id": 10034697, "course_code": "PHYS416"}, {"user_id": 10034708, "course_code": "ENGL122"}, {"user_id": 10034706, "course_code": "BIOL179"}, {"user_id": 10034689, "course_code": "PHYS597"}, {"user_id": 10034689, "course_code": "HIST207"}, {"user_id": 10034689, "course_code": "ENGL306"}, {"user_id": 10034689, "course_code": "ECON189"}, {"user_id": 10034674, "course_code": "LANG192"}, {"user_id": 10034674, "course_code": "MGMT547"}, {"user_id": 10034674, "course_code": "ENGL230"}, {"user_id": 10034674, "course_code": "ECON277"}, {"user_id": 10034672, "course_code": "COMP665"}, {"user_id": 10034672, "course_code": "LANG611"}]